<!DOCTYPE verb SYSTEM "verb.dtd">
<verb>
    <id> 筹购 </id>
    <frameset id="f1">
        <role argnum="0" argrole="agent"/>
        <role argnum="1" argrole="thing arg0 plans to purchase"/>
        <frame>
            <mapping>
                <V/>
                <mapitem src="sbj" trg="arg0"/>
                <mapitem src="npobj" trg="arg1"/>
            </mapping>
            <example>
                <parse>
                    (NP-SBJ (-NONE- *pro*))
                    (VP (VV 筹购)
                    (NP-OBJ (NN 武器)
                    (NN 装备)))) 
                    
                </parse>
                <arg n="0">
                    *pro*          
                </arg>
                <arg n="1">
                    武器 装备          
                </arg>
                <V/>
            </example>
        </frame>
    </frameset>
</verb>
