<!DOCTYPE verb SYSTEM "verb.dtd">
<verb>
    <id> 步履匆匆 </id>
    <frameset id="f1">
        <role argnum="0" argrole="agent"/>
        <frame>
            <mapping>
                <V/>
                <mapitem src="sbj" trg="arg0"/>
            </mapping>
            <example>
                <parse>
                    (NP-SBJ (DNP (QP (QP (CD 一)
                    (CLP (M 群)))
                    (QP (CD 一)
                    (CLP (M 群))))
                    (DEG 的))
                    (NP-PN (NR 香港))
                    (NP (NN 游客)))
                    (VP (VV 步履匆匆))) 
                    
                </parse>
                <arg n="0">
                    一 群 一 群 的 香港          
                </arg>
                <V/>
            </example>
        </frame>
    </frameset>
</verb>
