<!DOCTYPE verb SYSTEM "verb.dtd">
<verb>
    <id> 强健 </id>
    <frameset id="f1">
        <role argnum="0" argrole="entity described"/>
        <frame>
            <mapping>
                <V/>
                <mapitem src="sbj" trg="arg0"/>
            </mapping>
            <example>
                <parse>
                    (CP (WHNP-1 (-NONE- *OP*))
                    (CP (IP (NP-SBJ (-NONE- *T*-1))
                    (VP (VA 强健)))
                    (DEC 的)))
                    (NP (NN 体魄)
                    (CC 和)
                    (NN 战力))) 
                    
                </parse>
                <arg n="0">
                    *T*-1 -> 体魄 和 战力          
                </arg>
                <V/>
            </example>
        </frame>
    </frameset>
</verb>
